Metadata-Version: 1.0
Name: deep-dircmp
Version: 0.2.0
Summary: A recursive directory comparison
Home-page: https://github.com/mitar/python-deep-dircmp
Author: Mitar
Author-email: UNKNOWN
License: BSD
Platform: UNKNOWN
